Workbook

Sheet Cover
C11: Independent Financial Snapshot
C12: Position Green - Public Data Review (2023–2024)
C14: Prepared as part of application for FP&A role
C15: Felicia Nata
C18: Table of Contents | M18: Model Checks
C20: Inputs | M20: Balance Sheet Balanced? | Q20: =IF(SUM(Model!G132:M132)>0,1,0) -> 1
C21: Model
C36: This brief snapshot is based solely on publicly available information and is intended for discussion purposes only. The objective is to demonstrate analytical approach and driver-based thinking rather than provide a complete financial assessment.
C39: https://www.linkedin.com/in/yfelnt/

Sheet Inputs
B3: Drivers
H5: Year 1 | I5: Year 2 | J5: Year 3 | K5: Year 4 | L5: Year 5
B7: Driver Switch | E7: 2
B9: License Revenue Growth | H9: {=INDEX(H11:H13,$E$7)} -> 0.55 | I9: {=INDEX(I11:I13,$E$7)} -> 0.45 | J9: {=INDEX(J11:J13,$E$7)} -> 0.35 | K9: {=INDEX(K11:K13,$E$7)} -> 0.28 | L9: {=INDEX(L11:L13,$E$7)} -> 0.22
C11: Base Case | H11: 0.45 | I11: 0.35 | J11: 0.28 | K11: 0.22 | L11: 0.18
C12: Upside | H12: 0.55 | I12: 0.45 | J12: 0.35 | K12: 0.28 | L12: 0.22
C13: Downside | H13: 0.35 | I13: 0.28 | J13: 0.22 | K13: 0.18 | L13: 0.15
B16: Consulting Revenue Growth | H16: {=INDEX(H18:H20,$E$7)} -> 0.4 | I16: {=INDEX(I18:I20,$E$7)} -> 0.3 | J16: {=INDEX(J18:J20,$E$7)} -> 0.25 | K16: {=INDEX(K18:K20,$E$7)} -> 0.2 | L16: {=INDEX(L18:L20,$E$7)} -> 0.15
C18: Base Case | H18: 0.3 | I18: 0.25 | J18: 0.2 | K18: 0.15 | L18: 0.12
C19: Upside | H19: 0.4 | I19: 0.3 | J19: 0.25 | K19: 0.2 | L19: 0.15
C20: Downside | H20: 0.2 | I20: 0.15 | J20: 0.12 | K20: 0.1 | L20: 0.08
B23: Personnel Expenses Growth | H23: {=INDEX(H24:H26,$E$7)} -> 0.82 | I23: {=INDEX(I24:I26,$E$7)} -> 0.72 | J23: {=INDEX(J24:J26,$E$7)} -> 0.62 | K23: {=INDEX(K24:K26,$E$7)} -> 0.55 | L23: {=INDEX(L24:L26,$E$7)} -> 0.5
C24: Base Case | H24: 0.85 | I24: 0.8 | J24: 0.75 | K24: 0.7 | L24: 0.65
C25: Upside | H25: 0.82 | I25: 0.72 | J25: 0.62 | K25: 0.55 | L25: 0.5
C26: Downside | H26: 0.9 | I26: 0.88 | J26: 0.85 | K26: 0.82 | L26: 0.8
B29: Capital Expenditure | H29: {=INDEX(H30:H32,$E$7)} -> 0.08 | I29: {=INDEX(I30:I32,$E$7)} -> 0.07 | J29: {=INDEX(J30:J32,$E$7)} -> 0.06 | K29: {=INDEX(K30:K32,$E$7)} -> 0.05 | L29: {=INDEX(L30:L32,$E$7)} -> 0.04
C30: Base Case | H30: 0.06 | I30: 0.05 | J30: 0.04 | K30: 0.04 | L30: 0.03
C31: Upside | H31: 0.08 | I31: 0.07 | J31: 0.06 | K31: 0.05 | L31: 0.04
C32: Downside | H32: 0.05 | I32: 0.04 | J32: 0.035 | K32: 0.03 | L32: 0.03
B35: Other Inputs
B37: Interest Rates
C38: Long Term Debt | E38: =Model!H109 -> 102930
C39: Finance Expenses | E39: =Model!H57*-1 -> 11323
C40: Interest | E40: =E39/E38 -> 0.1100068
C42: Swedish corporate tax-rate | E42: 0.206
C43: Nordic short-term rates | E43: 0.035
B45: Useful Life Assumptions
C46: Goodwill | E46: 10 years
C47: Development Costs | E47: 10 years

Sheet Model
B3: Assumptions & Drivers
C5: All figures in TNOK thousands unless stated | G5: Year -1 | H5: Year 0 | I5: Year 1 | J5: Year 2 | K5: Year 3 | L5: Year 4 | M5: Year 5
C7: Days in Period (Days) | H7: 365 | I7: 365 | J7: =I7 -> 365 | K7: =J7 -> 365 | L7: =K7 -> 365 | M7: =L7 -> 365
C9: Revenue Drivers
C10: License Revenue Growth (%) | H10: =H176/G176-1 -> 1.0628195 | I10: =Inputs!H9 -> 0.55 | J10: =Inputs!I9 -> 0.45 | K10: =Inputs!J9 -> 0.35 | L10: =Inputs!K9 -> 0.28 | M10: =Inputs!L9 -> 0.22
C11: Consulting Revenue Growth (%) | H11: =H177/G177-1 -> 0.68602741 | I11: =Inputs!H16 -> 0.4 | J11: =Inputs!I16 -> 0.3 | K11: =Inputs!J16 -> 0.25 | L11: =Inputs!K16 -> 0.2 | M11: =Inputs!L16 -> 0.15
C12: Other Revenue (% of Revenue) | G12: =G40/G41 -> 0.0095962052 | H12: =H40/H41 -> 0.0040433037 | I12: =H12 -> 0.0040433037 | J12: =I12 -> 0.0040433037 | K12: =J12 -> 0.0040433037 | L12: =K12 -> 0.0040433037 | M12: =L12 -> 0.0040433037
C14: Cost of Revenue Drivers
C15: Cost of Goods Sold (% of Revenue) | G15: =G44/G41*-1 -> 0.040521561 | H15: =H44/H41*-1 -> 0.028562703 | I15: =H15 -> 0.028562703 | J15: =I15 -> 0.028562703 | K15: =J15 -> 0.028562703 | L15: =K15 -> 0.028562703 | M15: =L15 -> 0.028562703
C16: Personnel Expenses (% of Revenue) | I16: =Inputs!H23 -> 0.82 | J16: =Inputs!I23 -> 0.72 | K16: =Inputs!J23 -> 0.62 | L16: =Inputs!K23 -> 0.55 | M16: =Inputs!L23 -> 0.5
C17: Other Operating Expenses (% of Revenue) | G17: =G49/G41 -> -0.36118018 | H17: =H49/H41 -> -0.24292193 | I17: =H17 -> -0.24292193 | J17: =I17 -> -0.24292193 | K17: =J17 -> -0.24292193 | L17: =K17 -> -0.24292193 | M17: =L17 -> -0.24292193
C18: Operating Expenses | G18: =G48+G49 -> -275412 | H18: =H48+H49 -> -379117 | I18: =I48+I49 -> -505299.95 | J18: =J48+J49 -> -620400.06 | K18: =K48+K49 -> -716889.88 | L18: =L48+L49 -> -812242.25 | M18: =M48+M49 -> -898011
C20: Investments
C21: Capital Expenditure (% of Revenue) | I21: =I41*Inputs!H29 -> 38031.012 | J21: =J41*Inputs!I29 -> 45100.234 | K21: =K41*Inputs!J29 -> 49846.216 | L21: =L41*Inputs!K29 -> 51218.299 | M21: =M41*Inputs!L29 -> 48350.222
C23: Working Capital Drivers
C24: Trade Receivable (Days) | H24: =H92/H178*H7 -> 103.6967 | I24: =H24 -> 103.6967 | J24: =I24 -> 103.6967 | K24: =J24 -> 103.6967 | L24: =K24 -> 103.6967 | M24: =L24 -> 103.6967
C25: Account Payable (% of Operating Expenses) | H25: =H113/H18*-1 -> 0.038317986 | I25: =H25 -> 0.038317986 | J25: =I25 -> 0.038317986 | K25: =J25 -> 0.038317986 | L25: =K25 -> 0.038317986 | M25: =L25 -> 0.038317986
C26: Public Duties Payable | H26: =H114/H188*-1 -> 0.091427408 | I26: =H26 -> 0.091427408 | J26: =I26 -> 0.091427408 | K26: =J26 -> 0.091427408 | L26: =K26 -> 0.091427408 | M26: =L26 -> 0.091427408
C27: Other Current Liabilities | H27: =H115/H190*-1 -> 0.10883975 | I27: =H27 -> 0.10883975 | J27: =I27 -> 0.10883975 | K27: =J27 -> 0.10883975 | L27: =K27 -> 0.10883975 | M27: =L27 -> 0.10883975
C28: Deferred Revenue (% of Revenue) | H28: =H116/H41 -> 0.3038219 | I28: =H28 -> 0.3038219 | J28: =I28 -> 0.3038219 | K28: =J28 -> 0.3038219 | L28: =K28 -> 0.3038219 | M28: =L28 -> 0.3038219
C29: Other Current Receivables | H29: =H93/H41 -> 0.044583225 | I29: =H29 -> 0.044583225 | J29: =I29 -> 0.044583225 | K29: =MEDIAN(I29:J29) -> 0.044583225 | L29: =MEDIAN(J29:K29) -> 0.044583225 | M29: =MEDIAN(K29:L29) -> 0.044583225
C30: Other Non-Current Receivables | H30: =H84/H181 -> 0.042363073 | I30: =H30 -> 0.042363073 | J30: =I30 -> 0.042363073 | K30: =J30 -> 0.042363073 | L30: =K30 -> 0.042363073 | M30: =L30 -> 0.042363073
C31: Prepayment | H31: =H94/H181 -> 0.031524942 | I31: =H31 -> 0.031524942 | J31: =I31 -> 0.031524942 | K31: =J31 -> 0.031524942 | L31: =K31 -> 0.031524942 | M31: =L31 -> 0.031524942
B34: Consolidated Profit and Loss Account
C36: All figures in TNOK thousands unless stated | G36: Year -1 | H36: Year 0 | I36: Year 1 | J36: Year 2 | K36: Year 3 | L36: Year 4 | M36: Year 5
C38: Revenue
C39: Sales Revenue | G39: 181233 | H39: 326131 | I39: =I178 -> 473473.25 | J39: =J178 -> 641694.49 | K39: =K178 -> 827424.74 | L39: =L178 -> 1020240.8 | M39: =M178 -> 1203887.9
C40: Other Revenue | G40: 1756 | H40: 1324 | I40: =I180 -> 1914.3961 | J40: =J180 -> 2594.5657 | K40: =K180 -> 3345.5295 | L40: =L180 -> 4125.1435 | M40: =M180 -> 4867.6842
C41: Total Revenue | G41: =SUM(G39:G40) -> 182989 | H41: =SUM(H39:H40) -> 327455 | I41: =SUM(I39:I40) -> 475387.65 | J41: =SUM(J39:J40) -> 644289.06 | K41: =SUM(K39:K40) -> 830770.27 | L41: =SUM(L39:L40) -> 1024366 | M41: =SUM(M39:M40) -> 1208755.5
C43: Cost of Revenue
C44: Cost of goods sold | G44: -7415 | H44: -9353 | I44: =I15*I181*-1 -> -13578.356 | J44: =J15*J181*-1 -> -18402.637 | K44: =K15*K181*-1 -> -23729.045 | L44: =L15*L181*-1 -> -29258.662 | M44: =M15*M181*-1 -> -34525.326
C45: Gross Profit | G45: =G41+G44 -> 175574 | H45: =H41+H44 -> 318102 | I45: =I41+I44 -> 461809.29 | J45: =J41+J44 -> 625886.42 | K45: =K41+K44 -> 807041.23 | L45: =L41+L44 -> 995107.33 | M45: =M41+M44 -> 1174230.2
C47: Operating Expenses
C48: Personnel expenses | G48: -209320 | H48: -299571 | I48: =I188 -> -389817.87 | J48: =J188 -> -463888.12 | K48: =K188 -> -515077.57 | L48: =L188 -> -563401.29 | M48: =M188 -> -604377.77
C49: Other operating expenses | G49: -66092 | H49: -79546 | I49: =I189 -> -115482.08 | J49: =J189 -> -156511.94 | K49: =K189 -> -201812.32 | L49: =L189 -> -248840.96 | M49: =M189 -> -293633.23
C50: EBITDA | G50: =G45+G48+G49 -> -99838 | H50: =H45+H48+H49 -> -61015 | I50: =I45+I48+I49 -> -43490.664 | J50: =J45+J48+J49 -> 5486.3588 | K50: =K45+K48+K49 -> 90151.342 | L50: =L45+L48+L49 -> 182865.07 | M50: =M45+M48+M49 -> 276219.22
C52: Depreciation and amortization | G52: -49846 | H52: -56724 | I52: =I222*-1 -> -54684.473 | J52: =J222*-1 -> -58281.713 | K52: =K222*-1 -> -61994.155 | L52: =L222*-1 -> -65472.858 | M52: =M222*-1 -> -68317.15
C53: EBIT | G53: =G50+G52 -> -149684 | H53: =H50+H52 -> -117739 | I53: =I50+I52 -> -98175.136 | J53: =J50+J52 -> -52795.355 | K53: =K50+K52 -> 28157.187 | L53: =L50+L52 -> 117392.21 | M53: =M50+M52 -> 207902.07
C55: Financial income and expenses
C56: Finance income | G56: 3085 | H56: 5553 | I56: =I341 -> -1251.4815 | J56: =J341 -> -3833.6665 | K56: =K341 -> -2642.2223 | L56: =L341 -> 3223.0435 | M56: =M341 -> 14167.868
C57: Finance expense | G57: -3492 | H57: -11323 | I57: =I241*-1 -> -11323 | J57: =J241*-1 -> -11323 | K57: =K241*-1 -> -11323 | L57: =L241*-1 -> -11323 | M57: =M241*-1 -> -11323
C58: Net financial profit/loss | G58: =SUM(G56:G57) -> -407 | H58: =SUM(H56:H57) -> -5770 | I58: =SUM(I56:I57) -> -12574.481 | J58: =SUM(J56:J57) -> -15156.667 | K58: =SUM(K56:K57) -> -13965.222 | L58: =SUM(L56:L57) -> -8099.9565 | M58: =SUM(M56:M57) -> 2844.8684
C60: EBT | G60: =G53+G58 -> -150091 | H60: =H53+H58 -> -123509 | I60: =I53+I58 -> -110749.62 | J60: =J53+J58 -> -67952.021 | K60: =K53+K58 -> 14191.964 | L60: =L53+L58 -> 109292.26 | M60: =M53+M58 -> 210746.94
C62: Income tax expense | G62: 11518 | H62: -410 | I62: =I60*Inputs!$E$42 -> -22814.421 | J62: =J60*Inputs!$E$42 -> -13998.116 | K62: =K60*Inputs!$E$42 -> 2923.5446 | L62: =L60*Inputs!$E$42 -> 22514.205 | M62: =M60*Inputs!$E$42 -> 43413.869
C63: Net Income | G63: =G53+G58+G62 -> -138573 | H63: =H53+H58+H62 -> -123919 | I63: =I53+I58+I62 -> -133564.04 | J63: =J53+J58+J62 -> -81950.137 | K63: =K53+K58+K62 -> 17115.509 | L63: =L53+L58+L62 -> 131806.46 | M63: =M53+M58+M62 -> 254160.81
B66: Consolidated Balance Sheet
C68: All figures in TNOK thousands unless stated | G68: Year -1 | H68: Year 0 | I68: Year 1 | J68: Year 2 | K68: Year 3 | L68: Year 4 | M68: Year 5
C70: ASSETS
D71: Non-Current Assets
D72: Intangible assets
D73: Intangible assets | G73: 29663 | H73: 60118 | I73: =I209 -> 88334.111 | J73: =J209 -> 120090.91 | K73: =K209 -> 152943.41 | L73: =L209 -> 183745.54 | M73: =M209 -> 208886.19
D74: Deferred tax asset | G74: 20966 | H74: 21857 | I74: =I314 -> 44671.421 | J74: =J314 -> 58669.538 | K74: =K314 -> 55745.993 | L74: =L314 -> 33231.788 | M74: =M314 -> -10182.081
D75: Goodwill | G75: 363915 | H75: 319656 | I75: =I203 -> 275397 | J75: =J203 -> 231138 | K75: =K203 -> 186879 | L75: =L203 -> 142620 | M75: =M203 -> 98361
D76: Total intangible assets | G76: =SUM(G73:G75) -> 414544 | H76: =SUM(H73:H75) -> 401631 | I76: =SUM(I73:I75) -> 408402.53 | J76: =SUM(J73:J75) -> 409898.45 | K76: =SUM(K73:K75) -> 395568.41 | L76: =SUM(L73:L75) -> 359597.33 | M76: =SUM(M73:M75) -> 297065.11
D78: Tangible assets
D79: Operating assets, inventory etc. | G79: 6349 | H79: 5745 | I79: =I215 -> 6466.4286 | J79: =J215 -> 7119.1497 | K79: =K215 -> 7709.7068 | L79: =L215 -> 8244.0205 | M79: =M215 -> 8727.4471
D80: Total tangible assets | G80: =SUM(G79) -> 6349 | H80: =SUM(H79) -> 5745 | I80: =SUM(I79) -> 6466.4286 | J80: =SUM(J79) -> 7119.1497 | K80: =SUM(K79) -> 7709.7068 | L80: =SUM(L79) -> 8244.0205 | M80: =SUM(M79) -> 8727.4471
D82: Financial Non-Current Assets
D83: Investments in shares | G83: 11 | H83: 0 | I83: =I293 -> 0 | J83: =J293 -> 0 | K83: =K293 -> 0 | L83: =L293 -> 0 | M83: =M293 -> 0
D84: Other non-current receivables | G84: 4007 | H84: 13872 | I84: =I29*I181 -> 21194.314 | J84: =J29*J181 -> 28724.484 | K84: =K29*K181 -> 37038.418 | L84: =L29*L181 -> 45669.539 | M84: =M29*M181 -> 53890.221
D85: Total financial non-current assets | G85: =SUM(G83:G84) -> 4018 | H85: =SUM(H83:H84) -> 13872 | I85: =SUM(I83:I84) -> 21194.314 | J85: =SUM(J83:J84) -> 28724.484 | K85: =SUM(K83:K84) -> 37038.418 | L85: =SUM(L83:L84) -> 45669.539 | M85: =SUM(M83:M84) -> 53890.221
D88: Total non-current assets | G88: =G76+G80+G85 -> 424911 | H88: =H76+H80+H85 -> 421248 | I88: =I76+I80+I85 -> 436063.27 | J88: =J76+J80+J85 -> 445742.08 | K88: =K76+K80+K85 -> 440316.53 | L88: =L76+L80+L85 -> 413510.89 | M88: =M76+M80+M85 -> 359682.77
D90: Current Assets
D91: Receivable
D92: Trade Receivable | G92: 61729 | H92: 92654 | I92: =I255 -> 114377.58 | J92: =J255 -> 159515.59 | K92: =K255 -> 210145.44 | L92: =L255 -> 264293.38 | M92: =M255 -> 318143.34
D93: Other current receivables | G93: 8427 | H93: 14599 | I93: =I260 -> 17005.441 | J93: =J260 -> 23716.473 | K93: =K260 -> 31244.023 | L93: =L260 -> 39294.636 | M93: =M260 -> 47300.945
D94: Prepayments | G94: 8280 | H94: 10323 | I94: =I31*I181 -> 14986.568 | J94: =J31*J181 -> 20311.175 | K94: =K31*K181 -> 26189.985 | L94: =L31*L181 -> 32293.079 | M94: =M31*M181 -> 38105.949
D95: Total Receivables | G95: =SUM(G92:G94) -> 78436 | H95: =SUM(H92:H94) -> 117576 | I95: =SUM(I92:I94) -> 146369.59 | J95: =SUM(J92:J94) -> 203543.23 | K95: =SUM(K92:K94) -> 267579.45 | L95: =SUM(L92:L94) -> 335881.1 | M95: =SUM(M92:M94) -> 403550.24
D97: Cash and cash equivalents | G97: 43464 | H97: 71993 | I97: =I339 -> -35756.614 | J97: =J339 -> -109533.33 | K97: =K339 -> -75492.065 | L97: =L339 -> 92086.957 | M97: =M339 -> 404796.24
D98: Total current assets | G98: =G95+G97 -> 121900 | H98: =H95+H97 -> 189569 | I98: =I95+I97 -> 110612.98 | J98: =J95+J97 -> 94009.904 | K98: =K95+K97 -> 192087.38 | L98: =L95+L97 -> 427968.06 | M98: =M95+M97 -> 808346.48
D101: Total Assets | G101: =G98+G88 -> 546811 | H101: =H98+H88 -> 610817 | I101: =I98+I88 -> 546676.25 | J101: =J98+J88 -> 539751.99 | K101: =K98+K88 -> 632403.91 | L101: =L98+L88 -> 841478.95 | M101: =M98+M88 -> 1168029.2
C104: All figures in TNOK thousands unless stated | G104: Year -1 | H104: Year 0 | I104: Year 1 | J104: Year 2 | K104: Year 3 | L104: Year 4 | M104: Year 5
C106: EQUITY AND LIABILITIES
D107: Liabilities
D108: Non-current liabilities
D109: Long-term loan | G109: 0 | H109: 102930 | I109: 102930 | J109: =I109 -> 102930 | K109: =J109 -> 102930 | L109: =K109 -> 102930 | M109: =L109 -> 102930
D110: Total non-current liabilities | G110: =SUM(G109) -> 0 | H110: =SUM(H109) -> 102930 | I110: =SUM(I109) -> 102930 | J110: =SUM(J109) -> 102930 | K110: =SUM(K109) -> 102930 | L110: =SUM(L109) -> 102930 | M110: =SUM(M109) -> 102930
D112: Current liabilities
D113: Account payable | G113: 12872 | H113: 14527 | I113: =I265 -> 19362.077 | J113: =J265 -> 23772.481 | K113: =K265 -> 27469.777 | L113: =L265 -> 31123.488 | M113: =M265 -> 34409.973
D114: Public duties payable | G114: 20885 | H114: 27389 | I114: =I26*I188*-1 -> 35640.037 | J114: =J26*J188*-1 -> 42412.089 | K114: =K26*K188*-1 -> 47092.207 | L114: =L26*L188*-1 -> 51510.32 | M114: =M26*M188*-1 -> 55256.693
D115: Other current liabilities | G115: 18553 | H115: 41263 | I115: =I27*I190*-1 -> 54996.721 | J115: =J27*J190*-1 -> 67524.188 | K115: =K27*K190*-1 -> 78026.117 | L115: =L27*L190*-1 -> 88404.245 | M115: =M27*M190*-1 -> 97739.294
D116: Deferred revenue | G116: 46042 | H116: 99488 | I116: =I270 -> 144433.18 | J116: =J270 -> 195749.13 | K116: =K270 -> 252406.2 | L116: =L270 -> 311224.82 | M116: =M270 -> 367246.41
D117: Total current liabilities | G117: =SUM(G113:G116) -> 98352 | H117: =SUM(H113:H116) -> 182667 | I117: =SUM(I113:I116) -> 254432.01 | J117: =SUM(J113:J116) -> 329457.88 | K117: =SUM(K113:K116) -> 404994.3 | L117: =SUM(L113:L116) -> 482262.87 | M117: =SUM(M113:M116) -> 554652.37
D119: Total Liabilities | G119: =G110+G117 -> 98352 | H119: =H110+H117 -> 285597 | I119: =I110+I117 -> 357362.01 | J119: =J110+J117 -> 432387.88 | K119: =K110+K117 -> 507924.3 | L119: =L110+L117 -> 585192.87 | M119: =M110+M117 -> 657582.37
D121: Equity
D122: Paid-in equity
D123: Share capital | G123: 6383 | H123: 6396 | I123: 6396 | J123: =I123 -> 6396 | K123: =J123 -> 6396 | L123: =K123 -> 6396 | M123: =L123 -> 6396
D124: Share premium | G124: 636332 | H124: 639178 | I124: 639178 | J124: =I124 -> 639178 | K124: =J124 -> 639178 | L124: =K124 -> 639178 | M124: =L124 -> 639178
D125: Treasury shares | G125: -1022 | H125: -2040 | I125: -2040 | J125: =I125 -> -2040 | K125: =J125 -> -2040 | L125: =K125 -> -2040 | M125: =L125 -> -2040
D126: Other equity | G126: 3330 | H126: 1093 | I126: 1093 | J126: =I126 -> 1093 | K126: =J126 -> 1093 | L126: =K126 -> 1093 | M126: =L126 -> 1093
D127: Retained earnings | G127: -196564 | H127: -319407 | I127: =I327 -> -452970.04 | J127: =J327 -> -534920.18 | K127: =K327 -> -517804.67 | L127: =L327 -> -385998.2 | M127: =M327 -> -131837.4
D128: Total equity | G128: =SUM(G123:G127) -> 448459 | H128: =H101-H119 -> 325220 | I128: =I101-I119 -> 189314.24 | J128: =J101-J119 -> 107364.1 | K128: =K101-K119 -> 124479.61 | L128: =L101-L119 -> 256286.07 | M128: =M101-M119 -> 510446.88
D130: Total equity and liabilities | G130: =G119+G128 -> 546811 | H130: =H119+H128 -> 610817 | I130: =I119+I128 -> 546676.25 | J130: =J119+J128 -> 539751.99 | K130: =K119+K128 -> 632403.91 | L130: =L119+L128 -> 841478.95 | M130: =M119+M128 -> 1168029.2
D132: Balance Sheet Balanced? | G132: =IF((G101-G130)>=0,1,0) -> 1 | H132: =IF((H101-H130)>=0,1,0) -> 1 | I132: =IF((I101-I130)>=0,1,0) -> 1 | J132: =IF((J101-J130)>=0,1,0) -> 1 | K132: =IF((K101-K130)>=0,1,0) -> 1 | L132: =IF((L101-L130)>=0,1,0) -> 1 | M132: =IF((M101-M130)>=0,1,0) -> 1
B135: Consolidated Cash Flow
C137: All figures in TNOK thousands unless stated | I137: Year 1 | J137: Year 2 | K137: Year 3 | L137: Year 4 | M137: Year 5
C139: Net Income | I139: =I63 -> -133564.04 | J139: =J63 -> -81950.137 | K139: =K63 -> 17115.509 | L139: =L63 -> 131806.46 | M139: =M63 -> 254160.81
C141: Cash flow from operating activities
C142: Depreciation & Amortization | I142: =I222 -> 54684.473 | J142: =J222 -> 58281.713 | K142: =K222 -> 61994.155 | L142: =L222 -> 65472.858 | M142: =M222 -> 68317.15
C143: Change in Deferred Tax Asset (DTA) | I143: =I313*-1 -> -22814.421 | J143: =J313*-1 -> -13998.116 | K143: =K313*-1 -> 2923.5446 | L143: =L313*-1 -> 22514.205 | M143: =M313*-1 -> 43413.869
...
