Workbook

Sheet Cover
C13: Frauenthal Automotive – Group Performance & Profitability Analysis
C14: Sample Case Study
C16: Prepared as part of application for Group Business Controller role
C17: Felicia Nata
C20: Table of Contents
D22: Outputs | I22: Inputs
E23: The Big Picture | J23: Summary Statement of Profit or Loss (EUR million)
E24: Profitability Deep Dive | J24: Summary Statement of Financial Position (EUR million)
E25: Cost Structure Analysis | J25: Operational & Per Employee Metrics
E26: Financial Stability Section | J26: Additional Ratio
E27: Productivity Angle | J27: CONSOLIDATED STATEMENT OF PROFIT OR LOSS
E28: Strategic Recommendation | J28: CONSOLIDATED STATEMENT OF FINANCIAL POSITION
J29: CASH FLOW STATEMENT
J30: CHANGES IN FIXED ASSETS (2024)
C36: This analysis is based on publicly available financial information and simplified assumptions. The objective is to demonstrate financial analysis and performance interpretation.
C39: https://www.linkedin.com/in/yfelnt/

Sheet Output
K1: Group Performance & Profitability Analysis
B2: The Big Picture
B4: 5-Year Performance Overview: Growth, Peak, and Margin Compression
B22: "Revenue peaked in 2022 before declining in the following two years, while adjusted EBIT deteriorated significantly, indicating rising margin pressure despite relatively stable revenue levels."
B26: Profitability Deep Dive
B28: Margin Evolution & Operational Leverage
B47: Cost Structure Analysis
B49: % of Revenue | E49: 2023 | F49: 2024 | H49: Revenue (2024) | K49: -0.06
B51: Materials | E51: =Input!F50 -> 0.73564756 | F51: =Input!G50 -> 0.74995194
B52: Personnel | E52: =Input!F51 -> 0.15090946 | F52: =Input!G51 -> 0.1531355
B53: Other Opex | E53: =Input!F52 -> 0.063769813 | F53: =Input!G52 -> 0.063912684
B55: "Material costs increased from 74% to 75% of revenue, indicating reduced operating leverage as revenue declined."
B59: Financial Stability Section
B61: Balance Sheet Resilience Under Pressure | G61: 2023 | H61: 2024
B63: Debt/Equity | G63: =Input!F53 -> 1.6267535 | H63: =Input!G53 -> 1.8601285
B64: Interest Coverage | G64: =Input!F54 -> 2.5413461 | H64: =Input!G54 -> 0.50071518
B65: Equity Ratio | G65: =Input!F26 -> 0.381 | H65: =Input!G26 -> 0.35
B67: "Interest coverage dropped sharply from 2.54x to 0.50x due to declining EBIT, signaling increased pressure on debt servicing capacity."
B71: Productivity Angle
B90: "While revenue per employee continued to increase, EBIT per employee declined significantly after 2022, suggesting margin pressure at the operational level rather than productivity decline."
B94: Strategic Recommendation
B96: Management Focus Areas for 2025
B97: • Improve procurement efficiency to reduce material cost ratio
B98: • Protect margins through pricing discipline and product mix optimization
B99: • Increase cost flexibility during periods of declining volume
B100: • Strengthen interest coverage through EBIT recovery and balance sheet discipline
B101: • Prioritize CAPEX investments that enhance production efficiency

Sheet Input
G1: Group Performance & Profitability Analysis
B2: Summary Statement of Profit or Loss (EUR million)
B4: EUR million | C4: 2020 | D4: 2021 | E4: 2022 | F4: 2023 | G4: 2024
B5: Revenue | C5: 874 | D5: 1024.1 | E5: 1135.2 | F5: 1081 | G5: 1014.3
B6: EBITDA | C6: 37.7 | D6: 61.1 | E6: 99.1 | F6: 62.2 | G6: 47.6
B7: EBITDA (adjusted) | C7: 35.9 | D7: 61.1 | E7: 83.6 | F7: 62.2 | G7: 44.5
B8: Operating Profit (EBIT) | C8: -3.7 | D8: 22.3 | E8: 65.5 | F8: 28.7 | G8: 5.6
B9: EBIT (adjusted) | C9: 3.4 | D9: 27.2 | E9: 49.9 | F9: 28.7 | G9: 9.5
B10: Earnings Before Taxes (EBT) | C10: -10.8 | D10: 18.3 | E10: 60 | F10: 17.4 | G10: -5.6
B11: EBT (adjusted) | C11: -3.8 | D11: 23.2 | E11: 44.4 | F11: 17.4 | G11: -1.7
B12: Profit After Tax | C12: -14.7 | D12: 14.1 | E12: 48.5 | F12: 14.4 | G12: -5.1
B13: Earnings After Tax (adjusted) | C13: -5.9 | D13: 19.1 | E13: 48.5 | F13: 14.4 | G13: 0.7
B14: Earnings After Tax (adj. 1 & 2) | C14: -7.7 | D14: 19.1 | E14: 32.9 | F14: 14.4 | G14: -2.4
B15: Cash Flow from Earnings | C15: 34.7 | D15: 56.5 | E15: 74.4 | F15: 49.4 | G15: 29.7
B18: Summary Statement of Financial Position (EUR million)
B20: EUR million | C20: 2020 | D20: 2021 | E20: 2022 | F20: 2023 | G20: 2024
B21: Non-current Assets | C21: 188.2 | D21: 209.9 | E21: 201.3 | F21: 203.6 | G21: 189.3
B22: Current Assets | C22: 252.8 | D22: 286.8 | E22: 295.6 | F22: 300.9 | G22: 281.1
B23: Total Assets | C23: 441 | D23: 496.7 | E23: 496.9 | F23: 504.4 | G23: 470.4
B24: Total Liabilities | C24: 326.6 | D24: 368.1 | E24: 316 | F24: 312.4 | G24: 305.9
B25: Equity | C25: 114.4 | D25: 128.6 | E25: 180.9 | F25: 192 | G25: 164.5
B26: Equity Ratio (%) | C26: 0.259 | D26: 0.259 | E26: 0.364 | F26: 0.381 | G26: 0.35
B27: Investments | C27: 10.4 | D27: 21.3 | E27: 22 | F27: 21.5 | G27: 15.5
B28: Investments (% of Revenue) | C28: 0.012 | D28: 0.021 | E28: 0.021 | F28: 0.02 | G28: 0.015
B31: Operational & Per Employee Metrics
C33: 2020 | D33: 2021 | E33: 2022 | F33: 2023 | G33: 2024
B34: Average Employees | C34: 3292 | D34: 3255 | E34: 2837 | F34: 2862 | G34: 2583
B35: Revenue per Employee (EUR ‘000) | C35: 265.5 | D35: 314.6 | E35: 372.6 | F35: 377.7 | G35: 392.7
B36: EBIT per Employee (EUR ‘000) | C36: -1.1 | D36: 6.9 | E36: 17.4 | F36: 10 | G36: 2.2
B37: Cash Flow per Employee (EUR ‘000) | C37: 10.5 | D37: 17.4 | E37: 25.8 | F37: 17.2 | G37: 11.5
B38: Shares Issued | C38: 9434990 | D38: 9434990 | E38: 8651491 | F38: 8651491 | G38: 8651491
B39: Treasury Shares | C39: -793499 | D39: -783499 | E39: 0 | F39: 0 | G39: -865149
B40: Shares in Circulation | C40: 8641491 | D40: 8651491 | E40: 8651491 | F40: 8651491 | G40: 7786342
B43: Additional Ratio
C45: 2020 | D45: 2021 | E45: 2022 | F45: 2023 | G45: 2024
B47: EBITDA Margin (%) | C47: =C7/C5 -> 0.041075515 | D47: =D7/D5 -> 0.059662142 | E47: =E7/E5 -> 0.073643411 | F47: =F7/F5 -> 0.057539315 | G47: =G7/G5 -> 0.043872622
B48: EBIT Margin (%) | C48: =C9/C5 -> 0.0038901602 | D48: =D9/D5 -> 0.026559906 | E48: =E9/E5 -> 0.043957012 | F48: =F9/F5 -> 0.026549491 | G48: =G9/G5 -> 0.0093660653
B49: Net Margin (%) | C49: =C14/C5 -> -0.0088100686 | D49: =D14/D5 -> 0.018650522 | E49: =E14/E5 -> 0.028981677 | F49: =F14/F5 -> 0.013320999 | G49: =G14/G5 -> -0.0023661639
B50: Materials (% of Revenue) | F50: =-F66/F61 -> 0.73564756 | G50: =-G66/G61 -> 0.74995194
B51: Personnel (% of Revenue) | F51: =-F67/F61 -> 0.15090946 | G51: =-G67/G61 -> 0.1531355
B52: Other Opex (% of Revenue) | F52: =-F68/F61 -> 0.063769813 | G52: =-G68/G61 -> 0.063912684
B53: Debt/Equity | F53: =(F121+F131)/F112 -> 1.6267535 | G53: =(G121+G131)/G112 -> 1.8601285
B54: Interest Coverage Ratio | F54: =F72/-F73 -> 2.5413461 | G54: =G72/-G73 -> 0.50071518
B57: CONSOLIDATED STATEMENT OF PROFIT OR LOSS
F59: 2023 | G59: 2024
B60: (EUR ‘000)
B61: Revenue | F61: 1080966 | G61: 1014337
B62: Change in inventories | F62: 1233 | G62: -559
B63: Own work capitalised | F63: 7 | G63: 31
B64: Other operating income | F64: 7256 | G64: 14635
B65: Operating income total | F65: 1089462 | G65: 1028444
B66: Cost of materials | F66: -795210 | G66: -760704
B67: Personnel expenses | F67: -163128 | G67: -155331
B68: Other operating expenses | F68: -68933 | G68: -64829
B69: EBITDA | F69: 62191 | G69: 47580
B70: Depreciation & amortisation | F70: -33456 | G70: -35081
B71: Unscheduled depreciation | F71: 0 | G71: -6898
B72: EBIT | F72: 28735 | G72: 5601
... B77: EPS (Undiluted & Diluted) | F77: 1.66 | G77: -0.63
B80: CONSOLIDATED STATEMENT OF FINANCIAL POSITION
B82: (EUR ‘000) | F82: 2023 | G82: 2024
B83: ASSETS
B84: Long-term assets
B85: Intangible assets | F85: 20386 | G85: 18046
B86: Leasing licenses | F86: 70460 | G86: 69700
B87: Tangible assets | F87: 108118 | G87: 96703
B88: Financial assets | F88: 40 | G88: 40
B89: Other financial assets | F89: 2113 | G89: 2220
B90: Deferred tax assets | F90: 2468 | G90: 2587
B91: Total long-term assets | F91: 203585 | G91: 189296
B93: Short-term assets
B94: Inventories | F94: 203961 | G94: 182928
B95: Trade receivables | F95: 29986 | G95: 22477
B96: Tax receivables | F96: 1305 | G96: 1428
B97: Term deposit | F97: 9000 | G97: 0
B98: Other financial assets | F98: 10238 | G98: 14811
B99: Other non-financial assets | F99: 6529 | G99: 11010
B100: Cash & cash equivalents | F100: 39843 | G100: 48401
B101: Total short-term assets | F101: 300862 | G101: 281055
B103: TOTAL ASSETS | F103: =F101+F91 -> 504447 | G103: =G101+G91 -> 470351
B105: EQUITY AND LIABILITIES
B106: Equity
B107: Share capital | F107: 8652 | G107: 8652
B108: Capital reserve | F108: 22331 | G108: 22331
B109: Retained earnings | F109: 173039 | G109: 167930
B110: Other comprehensive income | F110: -11980 | G110: -13653
B111: Treasury shares | F111: 0 | G111: -20809
B112: Total equity | F112: 192042 | G112: 164451
B114: Liabilities
B115: Long-term Liabilities
B116: Financial liabilities | F116: 31205 | G116: 28754
B117: Leasing liabilities | F117: 55167 | G117: 54327
B118: Personnel provisions | F118: 34061 | G118: 33473
B119: Deferred tax liabilities | F119: 2952 | G119: 1915
B120: Other provisions | F120: 712 | G120: 751
B121: Total long-term liabilities | F121: 124097 | G121: 119220
B123: Short-term Liabilities
B124: Financial liabilities | F124: 24118 | G124: 37599
B125: Leasing liabilities | F125: 16562 | G125: 17245
B126: Trade payables | F126: 85018 | G126: 73064
...
