Workbook

Sheet Cover
C11: Strategic Financial Analysis
C12: Can Volvo Reach 8% EBIT Margin by 2026?
C15: Table of Contents | K15: Strategic Goal
D17: Dashboard | K17: EBIT 2026 > 8% | L17: =IF(Model!C127>0.08,1,2) -> 1
D18: Model
D19: Financial Data
D20: Model Query
C28: Prepared as part of application for Finance Business Office & Strategy
C30: Felicia Nata, CTP
C31: Strategic Finance & Treasury Professional | Turning Financial Insight into Executive Decision Support
C36: This brief snapshot is based solely on publicly available information and is intended for discussion purposes only. The objective is to demonstrate analytical approach and driver-based thinking rather than provide a complete financial assessment.

Sheet Dashboard
B3: VOLVO Profitability Dashboard | P3: Scenario
B4: Can Volvo Reach 8% EBIT Margin by 2026?
B7: Revenue (2025) | G7: EBIT Margin (2025) | M7: R&D Intensity
B8: =Model!J11 -> 357263 | G8: =Model!J13 -> 0.001 | M8: =Model!J28 -> 0.072963055
B11: =Model!J43 -> -0.10736469 | G11: =Model!J14 -> -0.055 | M11: of Revenue
K26: EBIT Margin Sensitivity (2026)
L27: Research and Development
H28: Volume | L28: =Model!G114 -> 0.07 | M28: =Model!H114 -> 0.06 | N28: =Model!I114 -> 0.05 | O28: =Model!J114 -> 0.04 | P28: =Model!K114 -> 0.03
H29: =Model!J41 -> -0.069881803 | J29: Gross Margin | K29: =Model!F115 -> 0.18 | L29: =Model!G115 -> 0.018 | M29: =Model!H115 -> 0.028 | N29: =Model!I115 -> 0.038 | O29: =Model!J115 -> 0.048 | P29: =Model!K115 -> 0.058
H30: Revenue | K30: =Model!F116 -> 0.19 | L30: =Model!G116 -> 0.028 | M30: =Model!H116 -> 0.038 | N30: =Model!I116 -> 0.048 | O30: =Model!J116 -> 0.058 | P30: =Model!K116 -> 0.068
H31: =Model!J43 -> -0.10736469 | K31: =Model!F117 -> 0.2 | L31: =Model!G117 -> 0.038 | M31: =Model!H117 -> 0.048 | N31: =Model!I117 -> 0.058 | O31: =Model!J117 -> 0.068 | P31: =Model!K117 -> 0.078
K32: =Model!F118 -> 0.21 | L32: =Model!G118 -> 0.048 | M32: =Model!H118 -> 0.058 | N32: =Model!I118 -> 0.068 | O32: =Model!J118 -> 0.078 | P32: =Model!K118 -> 0.088
K33: =Model!F119 -> 0.22 | L33: =Model!G119 -> 0.058 | M33: =Model!H119 -> 0.068 | N33: =Model!I119 -> 0.078 | O33: =Model!J119 -> 0.088 | P33: =Model!K119 -> 0.098
B36: Key Insights
B37: 🟩 Profitability collapsed in 2025 due to rising R&D
B38: 🟩 8% target achievable only in upside scenario | G38: Disclaimer: This analysis is based solely on publicly available information and is intended to demonstrate analytical approach and driver-based financial modeling rather than provide a full valuation.
B39: 🟩 Gross margin recovery is the biggest driver
B40: 🟩 R&D must decline toward -8% to restore margins

Sheet Model
K1: Can Volvo Reach 8% EBIT Margin by 2026?
B3: Trend Analysis
B5: KEY FINDING Volvo’s profitability deteriorated significantly in 2025 as gross margins declined and R&D investment surged during the EV transition. Sensitivity analysis suggests that reaching the 8% EBIT margin target in 2026 requires a meaningful recovery in gross margins combined with a normalization of R&D spending.
B8: REVENUE AND MARGIN TREND
B10: All figures in SEK million unless stated | F10: 2021 | G10: 2022 | H10: 2023 | I10: 2024 | J10: 2025
B11: Revenue | F11: ='Financial Data'!D127 -> 282045 | G11: ='Financial Data'!E127 -> 330145 | H11: ='Financial Data'!F127 -> 399343 | I11: ='Financial Data'!G127 -> 400234 | J11: ='Financial Data'!H127 -> 357263
B12: Gross Margin (%) | F12: ='Financial Data'!D138/100 -> 0.216 | G12: ='Financial Data'!E138/100 -> 0.183 | H12: ='Financial Data'!F138/100 -> 0.194 | I12: ='Financial Data'!G138/100 -> 0.198 | J12: ='Financial Data'!H138/100 -> 0.169
B13: EBIT Margin (%) | F13: ='Financial Data'!D139/100 -> 0.072 | G13: ='Financial Data'!E139/100 -> 0.068 | H13: ='Financial Data'!F139/100 -> 0.05 | I13: ='Financial Data'!G139/100 -> 0.056 | J13: ='Financial Data'!H139/100 -> 0.001
B14: Change EBIT Margin (%) | G14: =G13-F13 -> -0.004 | H14: =H13-G13 -> -0.018 | I14: =I13-H13 -> 0.006 | J14: =J13-I13 -> -0.055
B16: Volvo had very strong growth from 2021–2023, then:
B17: • growth stalled in 2024
B18: • revenue declined sharply in 2025
B19: So the issue is recent, not structural across the entire period.
B20: Volvo’s profitability had already been gradually declining before the sharp 2025 collapse.
B21: Volvo has not reached 8% EBIT margin in the last five years.
B24: RESEARCH AND DEVELOPMENT INTENSITY
B26: All figures in SEK million unless stated | F26: 2021 | G26: 2022 | H26: 2023 | I26: 2024 | J26: 2025
B27: Research and Development | F27: ='Financial Data'!D128 -> -12714 | G27: ='Financial Data'!E128 -> -11514 | H27: ='Financial Data'!F128 -> -12884 | I27: ='Financial Data'!G128 -> -16983 | J27: ='Financial Data'!H128 -> -26067
B28: % of Revenue | F28: =-F27/F11 -> 0.045077913 | G28: =-G27/G11 -> 0.034875585 | H28: =-H27/H11 -> 0.032262992 | I28: =-I27/I11 -> 0.042432677 | J28: =-J27/J11 -> 0.072963055
B30: R&D spending more than doubled relative to revenue.
B31: This aligns with:
B32: • EV platform investment
B33: • battery technology
B34: • software development
B35: The EV transition has significantly increased Volvo’s development costs.
B37: VOLUME VS REVENUE
B39: All figures in SEK million unless stated | F39: 2021 | G39: 2022 | H39: 2023 | I39: 2024 | J39: 2025
B40: Unit Solds | F40: ='Financial Data'!D126 -> 698693 | G40: ='Financial Data'!E126 -> 615121 | H40: ='Financial Data'!F126 -> 708716 | I40: ='Financial Data'!G126 -> 763389 | J40: ='Financial Data'!H126 -> 710042
B41: Unit Solds (% Change) | G41: =G40/F40-1 -> -0.1196119 | H41: =H40/G40-1 -> 0.15215706 | I41: =I40/H40-1 -> 0.077143736 | J41: =J40/I40-1 -> -0.069881803
B42: Revenue | F42: =F11 -> 282045 | G42: =G11 -> 330145 | H42: =H11 -> 399343 | I42: =I11 -> 400234 | J42: =J11 -> 357263
B43: Revenue (% Change) | G43: =G42/F42-1 -> 0.17054016 | H43: =H42/G42-1 -> 0.20959881 | I43: =I42/H42-1 -> 0.0022311647 | J43: =J42/I42-1 -> -0.10736469
B45: Volumes dropped 7% in 2025, but revenue dropped 11%.
B46: Meaning:
B47: • pricing pressure
B48: • weaker product mix
B49: • discounting
B51: CASH FLOW TREND
B53: All figures in SEK million unless stated | F53: 2021 | G53: 2022 | H53: 2023 | I53: 2024 | J53: 2025
B54: Operating Cash Flow | F54: ='Financial Data'!D135 -> 29852 | G54: ='Financial Data'!E135 -> 33599 | H54: ='Financial Data'!F135 -> 42867 | I54: ='Financial Data'!G135 -> 47372 | J54: ='Financial Data'!H135 -> 34625
B56: Cash flow grew strongly until 2024 but declined in 2025.
B58: INVESTMENT INTENSITY
B60: All figures in SEK million unless stated | F60: 2021 | G60: 2022 | H60: 2023 | I60: 2024 | J60: 2025
B61: Capital Expenditure | F61: ='Financial Data'!D136 -> -34737 | G61: ='Financial Data'!E136 -> -39658 | H61: ='Financial Data'!F136 -> -51842 | I61: ='Financial Data'!G136 -> -46245 | J61: ='Financial Data'!H136 -> -32176
B63: Volvo has been investing heavily for years, peaking in 2023.
B64: This reflects:
B65: • EV transition
B66: • factory upgrades
B67: • digital platforms
B69: INDUSTRY TRANSFORMATION INDICATOR
B71: All figures in SEK million unless stated | F71: 2021 | G71: 2022 | H71: 2023 | I71: 2024 | J71: 2025
B72: Electrified % | H72: ='Financial Data'!F156 -> 0.38 | I72: ='Financial Data'!G156 -> 0.46 | J72: ='Financial Data'!H156 -> 0.46
B74: Volvo is among the fastest electrifying automakers.
B75: But this transition creates:
B76: • high upfront costs
B77: • temporary margin pressure
B80: Scenario Analysis
B82: Scenario Switch | C82: 1
B84: Scenario
C85: Base | F85: EV costs stabilize and demand recovers
C86: Upside | F86: EV scale improves manufacturing eficiency
C87: Downside | F87: EV competition stay intense
B89: Driver | G89: Base | H89: Upside | I89: Downside
B90: Revenue Growth | F90: =CHOOSE($C$82,G90,H90,I90) -> 0.05 | G90: 0.05 | H90: 0.08 | I90: 0.02
B91: Gross Margin | F91: =CHOOSE($C$82,G91,H91,I91) -> 0.2 | G91: 0.2 | H91: 0.22 | I91: 0.18
B92: R&D % of Revenue | F92: =CHOOSE($C$82,G92,H92,I92) -> 0.055 | G92: 0.055 | H92: 0.045 | I92: 0.07
B93: Operating Expenses | F93: =CHOOSE($C$82,G93,H93,I93) -> 0.092 | G93: 0.092 | H93: 0.085 | I93: 0.1
B95: Can Volvo reach an 8% EBIT margin in 2026?
B97: All figures in SEK million unless stated | F97: 2021 | G97: 2022 | H97: 2023 | I97: 2024 | J97: 2025 | K97: 2026
B99: Revenue | F99: =F42 -> 282045 | G99: =G42 -> 330145 | H99: =H42 -> 399343 | I99: =I42 -> 400234 | J99: =J42 -> 357263 | K99: =J99*(1+F90) -> 375126.15
B100: Gross Margin | F100: =F12*F11 -> 60921.72 | G100: =G12*G11 -> 60416.535 | H100: =H12*H11 -> 77472.542 | I100: =I12*I11 -> 79246.332 | J100: =J12*J11 -> 60377.447 | K100: =K99*F91 -> 75025.23
B101: R&D Intensity | F101: =F27 -> -12714 | G101: =G27 -> -11514 | H101: =H27 -> -12884 | I101: =I27 -> -16983 | J101: =J27 -> -26067 | K101: =K99*-F92 -> -20631.938
B102: Operating Expenses | F102: =F103-F101-F100 -> -27932.72 | G102: =G103-G101-G100 -> -26570.535 | H102: =H103-H101-H100 -> -44649.542 | I102: =I103-I101-I100 -> -39945.332 | J102: =J103-J101-J100 -> -34007.447 | K102: =K99*(-F93) -> -34511.606
B103: EBIT | F103: ='Financial Data'!D129 -> 20275 | G103: ='Financial Data'!E129 -> 22332 | H103: ='Financial Data'!F129 -> 19939 | I103: ='Financial Data'!G129 -> 22318 | J103: ='Financial Data'!H129 -> 303 | K103: =SUM(K100:K102) -> 19881.686
B104: EBIT Margin | F104: =F103/F99 -> 0.071885692 | G104: =G103/G99 -> 0.067643005 | H104: =H103/H99 -> 0.049929509 | I104: =I103/I99 -> 0.055762379 | J104: =J103/J99 -> 0.00084811469 | K104: =K103/K99 -> 0.053
B107: EBIT Margin Sensitivity Analysis (2026)
B109: Drivers: Gross Margin vs R&D Intensity
B110: {=CONCATENATE("Model Running: ",INDEX(C85:C87,C82)," Scenario ")} -> Model Running: Base Scenario
B113: Revenue | C113: =J99*(1+F90) -> 375126.15 | G113: Research and Development
F114: =C119 -> 0.053 | G114: =0.07 -> 0.07 | H114: 0.06 | I114: 0.05 | J114: 0.04 | K114: 0.03
B115: Gross Margin | C115: =C113*F91 -> 75025.23 | E115: Gross Margin | F115: 0.18 | G115: 0.018 | H115: 0.028 | I115: 0.038 | J115: 0.048 | K115: 0.058
B116: R&D | C116: =F92*C113 -> 20631.938 | F116: 0.19 | G116: 0.028 | H116: 0.038 | I116: 0.048 | J116: 0.058 | K116: 0.068
B117: Operating Expenses | C117: =F93*C113 -> 34511.606 | F117: 0.2 | G117: 0.038 | H117: 0.048 | I117: 0.058 | J117: 0.068 | K117: 0.078
B118: EBIT | C118: =C115-C116-C117 -> 19881.686 | F118: 0.21 | G118: 0.048 | H118: 0.058 | I118: 0.068 | J118: 0.078 | K118: 0.088
B119: EBIT Margin | C119: =C118/C113 -> 0.053 | F119: 0.22 | G119: 0.058 | H119: 0.068 | I119: 0.078 | J119: 0.088 | K119: 0.098
B122: Key Takeaway: Volvo’s 8% EBIT margin target for 2026 appears achievable only under favorable conditions, particularly if gross margins recover significantly and R&D intensity declines as electrification investments stabilize.
B125: 2026 EBIT Margin Scenario Summary
B126: Base | C126: 0.053
B127: Upside | C127: 0.09
B128: Downside | C128: 0.01

Sheet Financial Data
H1: Can Volvo Reach 8% EBIT Margin by 2026?
B3: Income Statement
B5: All figures in SEK million unless stated | G5: Y2024 | H5: Y2025
B7: Revenue | G7: ='Model Query'!C180/1000000 -> 400234 | H7: ='Model Query'!D181/1000000 -> 357263
B8: Cost of Sales | G8: =-'Model Query'!C182/1000000 -> -320821 | H8: =-'Model Query'!D183/1000000 -> -297042
C9: Gross Income | G9: ='Model Query'!C184/1000000 -> 79413 | H9: ='Model Query'!D185/1000000 -> 60221
B11: Research And Development Expense | G11: =-'Model Query'!C186/1000000 -> -16983 | H11: =-'Model Query'!D187/1000000 -> -26067
B12: Selling Expense | G12: =-'Model Query'!C189/1000000 -> -25409 | H12: =-'Model Query'!D188/1000000 -> -23213
B13: Administrative Expense | G13: =-'Model Query'!C191/1000000 -> -12038 | H13: =-'Model Query'!D190/1000000 -> -10476
B14: Other Operating Income and Expense | G14: =('Model Query'!C193)/1000000 -> 2057 | H14: =('Model Query'!D192)/1000000 -> -816
B15: Share of Income in joint ventures and associates | G15: ='Model Query'!C195/1000000 -> -4722 | H15: ='Model Query'!D194/1000000 -> 654
C16: Operating Income | G16: ='Model Query'!C197/1000000 -> 22318 | H16: ='Model Query'!D196/1000000 -> 303
B18: Interest Income and Similar Credits | G18: ='Model Query'!C199/1000000 -> 2190 | H18: ='Model Query'!D198/1000000 -> 1929
B19: Interest Expense and Similar Changes | G19: =-'Model Query'!C201/1000000 -> -1164 | H19: =-'Model Query'!D200/1000000 -> -1251
B20: Other Financial Uncome and expenses | G20: ='Model Query'!C203/1000000 -> -625 | H20: ='Model Query'!D202/1000000 -> -1647
C21: Income Before Tax | G21: ='Model Query'!C205/1000000 -> 22719 | H21: ='Model Query'!D204/1000000 -> -666
B23: Income Tax | G23: =-'Model Query'!C207/1000000 -> -6785 | H23: =-'Model Query'!D206/1000000 -> -2302
C24: Net Income | G24: ='Model Query'!C208/1000000 -> 15934 | H24: ='Model Query'!D209/1000000 -> -2968
B26: Profit Loss Attributable To Owners Of Parent | G26: ='Model Query'!C210/1000000 -> 15401 | H26: ='Model Query'!D211/1000000 -> 174
B27: Profit Loss Attributable To Noncontrolling Interests | G27: ='Model Query'!C212/1000000 -> 533 | H27: ='Model Query'!D213/1000000 -> -3142
B30: Balance Sheet
B32: All figures in SEK million unless stated | G32: Y2024 | H32: Y2025
B34: ASSETS
B36: Non-Current Assets
B37: Intangible Assets And Goodwill | G37: ='Model Query'!C91/1000000 -> 83781 | H37: ='Model Query'!D92/1000000 -> 82965
B38: Property Plant And Equipment | G38: ='Model Query'!C93/1000000 -> 107124 | H38: ='Model Query'!D94/1000000 -> 99391
B39: Investment in Associates | G39: ='Model Query'!C95/1000000 -> 8998 | H39: ='Model Query'!D96/1000000 -> 7003
B40: Other Non-current Assets | G40: =('Model Query'!C97+'Model Query'!C100+'Model Query'!C102+'Model Query'!C104+'Model Query'!C106)/1000000 -> 29720 | H40: =('Model Query'!D98+'Model Query'!D99+'Model Query'!D101+'Model Query'!D103+'Model Query'!D105)/1000000 -> 26012
C41: Total Noncurrent Assets | G41: ='Model Query'!C108/1000000 -> 229623 | H41: ='Model Query'!D107/1000000 -> 215371
B43: Current Assets
B44: Inventories | G44: ='Model Query'!C110/1000000 -> 62455 | H44: ='Model Query'!D109/1000000 -> 59024
B45: Trade Receivables | G45: ='Model Query'!C111/1000000 -> 22780 | H45: ='Model Query'!D112/1000000 -> 21241
B46: Other Current Assets | G46: =('Model Query'!C113+'Model Query'!C115+'Model Query'!C117+'Model Query'!C119)/1000000 -> 17004 | H46: =('Model Query'!D114+'Model Query'!D116+'Model Query'!D118+'Model Query'!D120)/1000000 -> 19972
B47: Cash And Cash Equivalents | G47: ='Model Query'!C121/1000000 -> 56373 | H47: ='Model Query'!D122/1000000 -> 57564
C48: Total Current Assets | G48: ='Model Query'!C124/1000000 -> 158612 | H48: ='Model Query'!D123/1000000 -> 157801
B50: TOTAL ASSETS | G50: ='Model Query'!C126/1000000 -> 388235 | H50: ='Model Query'!D125/1000000 -> 373172
B52: EQUITY AND LIABILITIES
B54: EQUITY
B55: Equity Attributable To Owners Of Parent | G55: ='Model Query'!C128/1000000 -> 137461 | H55: ='Model Query'!D127/1000000 -> 147079
B56: Noncontrolling Interests | G56: ='Model Query'!C129/1000000 -> 4738 | H56: ='Model Query'!D130/1000000 -> 1299
C57: Total Equity | G57: ='Model Query'!C131/1000000 -> 142199 | H57: ='Model Query'!D132/1000000 -> 148378
B59: LIABILITIES
B60: Debt
B61: Long-Term Debt | G61: =('Model Query'!C139+'Model Query'!C141+'Model Query'!C146)/1000000 -> 30456 | H61: =('Model Query'!D140+'Model Query'!D142+'Model Query'!D145)/1000000 -> 33723
B62: Short-Term Debt | G62: =('Model Query'!C155+'Model Query'!C158+'Model Query'!C166)/1000000 -> 9272 | H62: =('Model Query'!D156+'Model Query'!D157+'Model Query'!D165)/1000000 -> 3992
C63: Total Debt | G63: =G61+G62 -> 39728 | H63: =H61+H62 -> 37715
B65: Operating Liabilities
B66: Trade And Other Current Payables To Trade Suppliers | G66: ='Model Query'!C162/1000000 -> 56479 | H66: ='Model Query'!D161/1000000 -> 57768
B67: Contract Liabilities | G67: =('Model Query'!C159+'Model Query'!C144)/1000000 -> 45752 | H67: =('Model Query'!D143+'Model Query'!D160)/1000000 -> 39869
B69: Other Liabilities
B70: Provisions | G70: =('Model Query'!C133+'Model Query'!C138+'Model Query'!C154)/1000000 -> 28991 | H70: =('Model Query'!D134+'Model Query'!D137+'Model Query'!D153)/1000000 -> 22737
B71: Tax Liabilities | G71: =('Model Query'!C135+'Model Query'!C163)/1000000 -> 12326 | H71: =('Model Query'!D136+'Model Query'!D164)/1000000 -> 11186
B72: Derivative Liabilities | G72: =('Model Query'!C148+'Model Query'!C167)/1000000 -> 4142 | H72: =('Model Query'!D147+'Model Query'!D168)/1000000 -> 738
B73: Other Liabilities | G73: =('Model Query'!C150+'Model Query'!C170)/1000000 -> 58618 | H73: =('Model Query'!D149+'Model Query'!D169)/1000000 -> 54781
C74: Total Liabilities | G74: =SUM(G63:G73) -> 246036 | H74: =SUM(H63:H73) -> 224794
B76: TOTAL EQUITY AND LIABILITIES | G76: =G57+G74 -> 388235 | H76: =H57+H74 -> 373172
B79: Cash Flow
B81: All figures in SEK million unless stated | G81: Y2024 | H81: Y2025
B83: OPERATING ACTIVITIES
B84: Operating Income | G84: ='Model Query'!D6/1000000 -> 22318 | H84: ='Model Query'!E7/1000000 -> 303
B85: Depreciation & amortization | G85: ='Model Query'!D8/1000000 -> 22730 | H85: ='Model Query'!E9/1000000 -> 23945
B86: Dividends Received | G86: ='Model Query'!D10/1000000 -> 213 | H86: ='Model Query'!E11/1000000 -> 205
B87: Interest Income | G87: ='Model Query'!D12/1000000 -> 2190 | H87: ='Model Query'!E13/1000000 -> 1929
B88: Interest Expense | G88: =-'Model Query'!D15/1000000 -> -1623 | H88: =-'Model Query'!E14/1000000 -> -1538
B89: Other Financial Items | G89: =-'Model Query'!D17/1000000 -> -836 | H89: =-'Model Query'!E16/1000000 -> -1963
B90: Income Taxes Paid | G90: =-'Model Query'!D19/1000000 -> -4448 | H90: =-'Model Query'!E18/1000000 -> -3724
B91: Other Adjustments For Non-cash Items | G91: =('Model Query'!D21)/1000000 -> 2754 | H91: =('Model Query'!E20)/1000000 -> 6281
G92: ='Model Query'!D23/1000000 -> 43298 | H92: ='Model Query'!E22/1000000 -> 25438
B94: Change in Inventory | G94: ='Model Query'!D25/1000000 -> -2757 | H94: ='Model Query'!E24/1000000 -> 2353
B95: Change in Receivable | G95: ='Model Query'!D26/1000000 -> -1386 | H95: ='Model Query'!E27/1000000 -> -84
B96: Change in Payable | G96: ='Model Query'!D28/1000000 -> -7539 | H96: ='Model Query'!E29/1000000 -> 7205
B97: Change in Provisions | G97: ='Model Query'!D30/1000000 -> -1905 | H97: ='Model Query'!E31/1000000 -> -1867
B98: Change in Contract Liabilities | G98: ='Model Query'!D32/1000000 -> 8709 | H98: ='Model Query'!E33/1000000 -> 644
B99: Other Working Capital | G99: =-'Model Query'!D34/1000000 -> 8952 | H99: =-'Model Query'!E35/1000000 -> 936
B100: Cash Flows from Operating Activities | G100: ='Model Query'!D38/1000000 -> 47372 | H100: ='Model Query'!E39/1000000 -> 34625
B102: INVESTING ACTIVITIES
B103: Net Equity Investment | G103: =(-'Model Query'!D41+'Model Query'!D43)/1000000 -> -2118 | H103: =(-'Model Query'!E40+'Model Query'!E42)/1000000 -> 7996
B104: Net Related-Party Loans | G104: =(-'Model Query'!D44+'Model Query'!D47)/1000000 -> -75 | H104: =(-'Model Query'!E45+'Model Query'!E46)/1000000 -> -1039
B105: Net Capital Expenditure | G105: =(-'Model Query'!D48-'Model Query'!D51)/1000000 -> -45033 | H105: =(-'Model Query'!E49-'Model Query'!E50)/1000000 -> -40077
B106: Disposal of Tangible Assets | G106: ='Model Query'!D53/1000000 -> 981 | H106: ='Model Query'!E52/1000000 -> 872
B107: Other Investing | G107: ='Model Query'!D54/1000000 -> 0 | H107: ='Model Query'!E55/1000000 -> 72
B108: Cash Flows From Used In Investing Activities | G108: ='Model Query'!D56/1000000 -> -46245 | H108: ='Model Query'!E57/1000000 -> -32176
B110: FINANCING ACTIVITIES
B111: Debt Issued | G111: =('Model Query'!D61+'Model Query'!D63)/1000000 -> 6056 | H111: =('Model Query'!E60+'Model Query'!E62)/1000000 -> 10423
B112: Debt Repaid | G112: =(-'Model Query'!D66-'Model Query'!D69-'Model Query'!D71)/1000000 -> -9851 | H112: =(-'Model Query'!E67-'Model Query'!E68-'Model Query'!E70)/1000000 -> -9471
B113: Equity Transactions | G113: =-'Model Query'!D65/1000000 -> -190 | H113: =-'Model Query'!E64/1000000 -> -219
B114: Net Other Financing | G114: =('Model Query'!D73+'Model Query'!D75)/1000000 -> 9901 | H114: =('Model Query'!E72+'Model Query'!E74)/1000000 -> 995
B115: Cash Flows From Used In Financing Activities | G115: ='Model Query'!D76/1000000 -> 5916 | H115: ='Model Query'!E77/1000000 -> 1728
B117: Cash And Cash Equivalents Beginning of Year | G117: ='Model Query'!C80/1000000 -> 47861 | H117: =G120 -> 56373
B118: Change in Cash Flow | G118: =G100+G108+G115 -> 7043 | H118: =H100+H108+H115 -> 4177
B119: Effect Of Exchange Rate Changes | G119: ='Model Query'!D82/1000000 -> 1469 | H119: ='Model Query'!E83/1000000 -> -2986
B120: Cash And Cash Equivalents End of Year | G120: ='Model Query'!D85/1000000 -> 56373 | H120: ='Model Query'!E84/1000000 -> 57564
B123: Key Ratio Table
B125: All figures in SEK million unless stated | D125: 2021 | E125: 2022 | F125: 2023 | G125: 2024 | H125: 2025
B126: Retail sales, units | D126: 698693 | E126: 615121 | F126: 708716 | G126: 763389 | H126: 710042
B127: Revenue (SEKm) | D127: 282045 | E127: 330145 | F127: 399343 | G127: 400234 | H127: 357263
B128: Research and development expenses | D128: -12714 | E128: -11514 | F128: -12884 | G128: -16983 | H128: -26067
B129: Operating income (EBIT) | D129: 20275 | E129: 22332 | F129: 19939 | G129: 22318 | H129: 303
B130: EBIT excl. share of income from JVs and associates | D130: 21226 | E130: 17889 | F130: 25567 | G130: 27040 | H130: -351
B131: EBIT excl. items affecting comparability | D131: 16995 | E131: 16433 | F131: 20563 | G131: 24020 | H131: 12556
...

Sheet Model Query
E1: Can Volvo Reach 8% EBIT Margin by 2026?
B3: Query - Cash Flow
B5: Account | C5: 2023 | D5: 2024 | E5: 2025
B6: Profit Loss From Operating Activities | D6: 22318000000
B7: Profit Loss From Operating Activities | E7: 303000000
B8: Adjustments For Depreciation And Amortisation Expense | D8: 22730000000
B9: Adjustments For Depreciation And Amortisation Expense | E9: 23945000000
B10: Dividends Received Classified As Operating Activities | D10: 213000000
B11: Dividends Received Classified As Operating Activities | E11: 205000000
B12: Interest Received Classified As Operating Activities | D12: 2190000000
B13: Interest Received Classified As Operating Activities | E13: 1929000000
B14: Interest Paid Classified As Operating Activities | E14: 1538000000
B15: Interest Paid Classified As Operating Activities | D15: 1623000000
B16: Finance Costs Paid And Finance Income Received Classified As Operating Activities | E16: 1963000000
B17: Finance Costs Paid And Finance Income Received Classified As Operating Activities | D17: 836000000
B18: Income Taxes Paid Classified As Operating Activities | E18: 3724000000
B19: Income Taxes Paid Classified As Operating Activities | D19: 4448000000
B20: Other Adjustments For Noncash Items | E20: 6281000000
B21: Other Adjustments For Noncash Items | D21: 2754000000
B22: Cash Flows From Used In Operations Before Changes In Working Capital | E22: 25438000000
B23: Cash Flows From Used In Operations Before Changes In Working Capital | D23: 43298000000
B24: Adjustments For Decrease Increase In Inventories | E24: 2353000000
B25: Adjustments For Decrease Increase In Inventories | D25: -2757000000
B26: Adjustments For Decrease Increase In Trade Account Receivable | D26: -1386000000
B27: Adjustments For Decrease Increase In Trade Account Receivable | E27: -84000000
B28: Adjustments For Increase Decrease In Trade Account Payable | D28: -7539000000
B29: Adjustments For Increase Decrease In Trade Account Payable | E29: 7205000000
B30: Adjustments For Provisions | D30: -1905000000
B31: Adjustments For Provisions | E31: -1867000000
B32: Adjustments For Increase Decrease In Contract Liabilities | D32: 8709000000
B33: Adjustments For Increase Decrease In Contract Liabilities | E33: 644000000
B34: Increase Decrease In Other Working Capital | D34: -8952000000
B35: Increase Decrease In Other Working Capital | E35: -936000000
B36: Increase Decrease In Working Capital | D36: -4074000000
B37: Increase Decrease In Working Capital | E37: -9187000000
B38: Cash Flows From Used In Operating Activities | D38: 47372000000
B39: Cash Flows From Used In Operating Activities | E39: 34625000000
B40: Investments In Shares And Participations Classified As Investing Activities | E40: -280000000
B41: Investments In Shares And Participations Classified As Investing Activities | D41: 1901000000
B42: Divestments In Shares And Participations Classified As Investing Activities | E42: 7716000000
B43: Divestments In Shares And Participations Classified As Investing Activities | D43: -217000000
B44: Cash Advances And Loans Made To Related Parties | D44: 75000000
B45: Cash Advances And Loans Made To Related Parties | E45: 2727000000
B46: Cash Receipts From Repayment Of Advances And Loans Made To Related Parties | E46: 1688000000
B47: Cash Receipts From Repayment Of Advances And Loans Made To Related Parties | D47: 0
B48: Purchase Of Intangible Assets Classified As Investing Activities | D48: 19774000000
B49: Purchase Of Intangible Assets Classified As Investing Activities | E49: 17252000000
B50: Purchase Of Property Plant And Equipment Classified As Investing Activities | E50: 22825000000
B51: Purchase Of Property Plant And Equipment Classified As Investing Activities | D51: 25259000000
B52: Proceeds From Sales Of Property Plant And Equipment Classified As Investing Activities | E52: 872000000
B53: Proceeds From Sales Of Property Plant And Equipment Classified As Investing Activities | D53: 981000000
B54: Other Inflows Outflows Of Cash Classified As Investing Activities | D54: 0
B55: Other Inflows Outflows Of Cash Classified As Investing Activities | E55: 72000000
B56: Cash Flows From Used In Investing Activities | D56: -46245000000
B57: Cash Flows From Used In Investing Activities | E57: -32176000000
B58: Cash Flows From Used In Operating And Investing Activities | E58: 2449000000
B59: Cash Flows From Used In Operating And Investing Activities | D59: 1127000000
B60: Proceeds From Borrowings Classified As Financing Activities | E60: 4947000000
B61: Proceeds From Borrowings Classified As Financing Activities | D61: 199000000
B62: Proceeds From Issue Of Bonds Notes And Debentures | E62: 5476000000
B63: Proceeds From Issue Of Bonds Notes And Debentures | D63: 5857000000
B64: Payments To Acquire Or Redeem Entitys Shares | E64: 219000000
B65: Payments To Acquire Or Redeem Entitys Shares | D65: 190000000
B66: Repayments Of Bonds Notes And Debentures | D66: 6936000000
B67: Repayments Of Bonds Notes And Debentures | E67: 5732000000
B68: Repayments Of Borrowings Classified As Financing Activities | E68: 1631000000
B69: Repayments Of Borrowings Classified As Financing Activities | D69: 862000000
B70: Repayments Of Interest Bearing Liabilities Classified As Financing Activities | E70: 2108000000
B71: Repayments Of Interest Bearing Liabilities Classified As Financing Activities | D71: 2053000000
B72: Matured Investments In Marketable Securities Classified As Financing Activities | E72: -1000000
B73: Matured Investments In Marketable Securities Classified As Financing Activities | D73: 10269000000
B74: Other Inflows Outflows Of Cash Classified As Financing Activities | E74: 996000000
B75: Other Inflows Outflows Of Cash Classified As Financing Activities | D75: -368000000
B76: Cash Flows From Used In Financing Activities | D76: 5916000000
B77: Cash Flows From Used In Financing Activities | E77: 1728000000
B78: Increase Decrease In Cash And Cash Equivalents Before Effect Of Exchange Rate Changes | D78: 7043000000
B79: Increase Decrease In Cash And Cash Equivalents Before Effect Of Exchange Rate Changes | E79: 4177000000
B80: Cash And Cash Equivalents | C80: 47861000000
B81: Cash And Cash Equivalents | D81: 56373000000
B82: Effect Of Exchange Rate Changes On Cash And Cash Equivalents | D82: 1469000000
B83: Effect Of Exchange Rate Changes On Cash And Cash Equivalents | E83: -2986000000
B84: Cash And Cash Equivalents | E84: 57564000000
B85: Cash And Cash Equivalents | D85: 56373000000
B88: Query - Balance Sheet
B90: Account | C90: 2024 | D90: 2025
B91: Intangible Assets And Goodwill | C91: 83781000000
B92: Intangible Assets And Goodwill | D92: 82965000000
B93: Property Plant And Equipment Including Rightofuse Assets | C93: 107124000000
B94: Property Plant And Equipment Including Rightofuse Assets | D94: 99391000000
B95: Investment Accounted For Using Equity Method | C95: 8998000000
B96: Investment Accounted For Using Equity Method | D96: 7003000000
B97: Other Noncurrent Financial Assets | C97: 12753000000
B98: Other Noncurrent Financial Assets | D98: 10454000000
B99: Deferred Tax Assets | D99: 8363000000
B100: Deferred Tax Assets | C100: 12260000000
B101: Other Noncurrent Receivables | D101: 1235000000
B102: Other Noncurrent Receivables | C102: 1440000000
B103: Noncurrent Derivative Financial Assets | D103: 1743000000
B104: Noncurrent Derivative Financial Assets | C104: 283000000
B105: Other Noncurrent Assets | D105: 4217000000
...
